eveunicalendar/__init__.py
eveunicalendar/admin.py
eveunicalendar/app_settings.py
eveunicalendar/apps.py
eveunicalendar/auth_hooks.py
eveunicalendar/models.py
eveunicalendar/signals.py
eveunicalendar/tasks.py
eveunicalendar/urls.py
eveunicalendar/utils.py
eveunicalendar/views.py
eveunicalendar/management/commands/__init__.py
eveunicalendar/management/commands/populate_events.py
eveunicalendar/migrations/0001_initial.py
eveunicalendar/migrations/0002_event_creator_global_name.py
eveunicalendar/migrations/0003_event_recurrence_rule.py
eveunicalendar/migrations/__init__.py
eveunicalendar/templates/eveunicalendar/base.html
eveunicalendar/templates/eveunicalendar/index.html
eveunicalendar/tests/__init__.py
eveunicalendar/tests/test_tasks.py
aa_eveunicalendar-0.9.0.dist-info/LICENSE
aa_eveunicalendar-0.9.0.dist-info/WHEEL
aa_eveunicalendar-0.9.0.dist-info/METADATA
aa_eveunicalendar-0.9.0.dist-info/RECORD
