Metadata-Version: 2.3
Name: aa-eveunicalendar
Version: 0.9.0
Summary: aa-eveunicalendar plugin app for Alliance Auth.
Author-email: Bates Larsson <bateslarsson@gmail.com>
Requires-Python: >=3.8
Classifier: Environment :: Web Environment
Classifier: Framework :: Django
Classifier: Framework :: Django :: 4.0
Classifier: Framework :: Django :: 4.2
Classifier: Intended Audience :: Developers
Classifier: License :: OSI Approved :: MIT License
Classifier: Operating System :: OS Independent
Classifier: Programming Language :: Python
Classifier: Programming Language :: Python :: 3.8
Classifier: Programming Language :: Python :: 3.9
Classifier: Programming Language :: Python :: 3.10
Classifier: Programming Language :: Python :: 3.11
Classifier: Topic :: Internet :: WWW/HTTP
Classifier: Topic :: Internet :: WWW/HTTP :: Dynamic Content
Requires-Dist: allianceauth>=3
Requires-Dist: google-api-python-client>=2
Requires-Dist: google-auth-httplib2>=0.2
Requires-Dist: google-auth-oauthlib>=1.2
Project-URL: Documentation, https://github.com/EVE-University/aa-eveunicalendar
Project-URL: Homepage, https://github.com/EVE-University/aa-eveunicalendar
Project-URL: Source, https://github.com/EVE-University/aa-eveunicalendar
Project-URL: Tracker, https://github.com/EVE-University/aa-eveunicalendar/issues
